{
    "CommandName": "div",
    "TagOpen": "div",
    "TagClose": "</div>",
    "BlockType": "BLOCK",
    "CommandPerposes": ["HTML","CSS","SCRIPT"],
    "CommandAlias": "div",
    "DocumentType": ["HTML4_LOOSE","HTML4_STRICT","XHTML1","HTML5"],
    "TagAttributes": {
        "HTML4_LOOSE": ["id","name","float"],
        "HTML4_STRICT": ["id","name","float"],
        "XHTML1": ["id","name","float"],
        "HTML5": ["id","name","float"]
    },
    "CustomAttributes": {
        "key": {
            "type": ["value"]
        }
    }
}
