{
    "CommandName": "defterm",
    "TagOpen": "dt",
    "TagClose": "</dt>",
    "BlockType": "ONELINE",
    "CommandPerposes": ["HTML"],
    "DocumentType": ["HTML4_LOOSE","HTML4_STRICT","HTML4_FRAME","XHTML1_LOOSE","XHTML1_STRICT","XHTML1_FRAME","XHTML1_1","HTML5","HTML5_1"],
    "TagAttributes": {
        "HTML4_LOOSE": {},
        "HTML4_STRICT": {},
        "HTML4_FRAME": {},
        "XHTML1_LOOSE": {},
        "XHTML1_STRICT": {},
        "XHTML1_FRAME": {},
        "XHTML1_1": {},
        "HTML5": {},
        "HTML5_1": {}
    }
}
